__basicest__.py
basicest/__init__.py
basicest/__main__.py
basicest/serve/__init__.py
basicest/serve/__main__.py
basicest/serve/build.py
basicest/serve/filter.py
basicest/serve/middleware.py
basicest/serve/server.py
basicest/serve/utils.py
basicest-0.5.0.dist-info/METADATA
basicest-0.5.0.dist-info/WHEEL
basicest-0.5.0.dist-info/entry_points.txt
basicest-0.5.0.dist-info/RECORD
